MANIFEST.in
README.md
setup.py
pyflow/__init__.py
pyflow/decider.py
pyflow/decision_task_helper.py
pyflow/event_handler.py
pyflow/exceptions.py
pyflow/future.py
pyflow/invocation_descriptors.py
pyflow/utils.py
pyflow/workflow.py
pyflow/workflow_invocation_helper.py
pyflow/workflow_state.py
pyflow_swf.egg-info/PKG-INFO
pyflow_swf.egg-info/SOURCES.txt
pyflow_swf.egg-info/dependency_links.txt
pyflow_swf.egg-info/requires.txt
pyflow_swf.egg-info/top_level.txt