Metadata-Version: 1.1
Name: pyflow-swf
Version: 1.6.3
Summary: Python Workflow Library built on the AWS SWF service
Home-page: https://github.com/ajenkins-cargometrics/pyflow
Author: Adam Jenkins
Author-email: adam@thejenkins.org
License: MIT
Platform: UNKNOWN
Classifier: Development Status :: 3 - Alpha
Classifier: Intended Audience :: Developers
Classifier: Topic :: Software Development :: Libraries :: Python Modules
Classifier: License :: OSI Approved :: MIT License
Classifier: Programming Language :: Python :: 2.7
